LICENSE
MANIFEST.in
README.rst
setup.py
tests/all_tests.py
yamgl_gen/__init__.py
yamgl_gen/__main__.py
yamgl_gen/bitmap.py
yamgl_gen/code.py
yamgl_gen/font.py
yamgl_gen/generator.py
yamgl_gen/image.py
yamgl_gen/parser.py
yamgl_gen/schema.xsd
yamgl_gen/yamgl_gen.py
yamgl_gen.egg-info/PKG-INFO
yamgl_gen.egg-info/SOURCES.txt
yamgl_gen.egg-info/dependency_links.txt
yamgl_gen.egg-info/entry_points.txt
yamgl_gen.egg-info/top_level.txt