Metadata-Version: 1.0
Name: yamgl-gen
Version: 0.0.4
Summary: Data structure generator for the yamgl library (Yet Another Monochrome Graphics Library).
Home-page: https://github.com/iocapa/yamgl_gen
Author: Ionut-Catalin Pavel
Author-email: pavel.ionut.catalin.88@gmail.com
License: UNKNOWN
Platform: UNKNOWN
